AUTHORS
CHANGELOG.txt
DESCRIPTION
LICENSE
MANIFEST.in
setup.py
cmsplugin_blog_authors/__init__.py
cmsplugin_blog_authors/admin.py
cmsplugin_blog_authors/models.py
cmsplugin_blog_authors.egg-info/PKG-INFO
cmsplugin_blog_authors.egg-info/SOURCES.txt
cmsplugin_blog_authors.egg-info/dependency_links.txt
cmsplugin_blog_authors.egg-info/top_level.txt
cmsplugin_blog_authors/migrations/0001_initial.py
cmsplugin_blog_authors/migrations/__init__.py
cmsplugin_blog_authors/tests/__init__.py
cmsplugin_blog_authors/tests/factories.py
cmsplugin_blog_authors/tests/models_tests.py
cmsplugin_blog_authors/tests/runtests.py
cmsplugin_blog_authors/tests/south_settings.py
cmsplugin_blog_authors/tests/test_settings.py
cmsplugin_blog_authors/tests/urls.py
cmsplugin_blog_authors/tests/test_app/__init__.py
cmsplugin_blog_authors/tests/test_app/models.py
cmsplugin_blog_authors/tests/test_app/templates/base.html
cmsplugin_blog_authors/tests/test_app/templates/standard.html