Metadata-Version: 1.0
Name: cmsplugin-blog-authors
Version: 0.1
Summary: Allows to add django-people objects to a cmsplugin-blog Entry.
